finbox_bankconnect/__init__.py
finbox_bankconnect/connector.py
finbox_bankconnect/custom_exceptions.py
finbox_bankconnect/entity.py
finbox_bankconnect/filters.py
finbox_bankconnect/utils.py
finbox_bankconnect-0.0.2.dist-info/LICENSE
finbox_bankconnect-0.0.2.dist-info/METADATA
finbox_bankconnect-0.0.2.dist-info/WHEEL
finbox_bankconnect-0.0.2.dist-info/top_level.txt
finbox_bankconnect-0.0.2.dist-info/RECORD
