Metadata-Version: 2.1
Name: finbox-bankconnect
Version: 0.0.2
Summary: Python library to use Finbox Bank Connect
Home-page: https://github.com/finbox-in/bank-connect-python
Author: FinBox
Author-email: tech@finbox.in
License: UNKNOWN
Platform: UNKNOWN
Classifier: Programming Language :: Python :: 3
Classifier: License :: OSI Approved :: MIT License
Classifier: Operating System :: OS Independent
Requires-Python: >=3.4
Requires-Dist: requests
